wifimeter/__init__.py
wifimeter/__main__.py
wifimeter/cli.py
wifimeter/network/__init__.py
wifimeter/network/tcp.py
wifimeter/network/threads.py
wifimeter/network/udp.py
wifimeter/util/__init__.py
wifimeter/util/coder.py
wifimeter/util/model.py
wifimeter/util/output.py
wifimeter/util/setup.py
wifimeter-0.1.1.dist-info/LICENSE
wifimeter-0.1.1.dist-info/METADATA
wifimeter-0.1.1.dist-info/WHEEL
wifimeter-0.1.1.dist-info/entry_points.txt
wifimeter-0.1.1.dist-info/top_level.txt
wifimeter-0.1.1.dist-info/RECORD
