Metadata-Version: 2.1
Name: wifimeter
Version: 0.1.1
Summary: Wifi Electricity Meter
Home-page: https://github.com/deddiag/wifimeter.git
License: MIT License
Platform: UNKNOWN
Classifier: Programming Language :: Python :: 3
Classifier: Programming Language :: Python :: 2
Classifier: License :: OSI Approved :: MIT License
Classifier: Operating System :: OS Independent
Requires-Python: >=2.7
Requires-Dist: pytz
Requires-Dist: click
Requires-Dist: timeout-decorator
